Metadata-Version: 2.4
Name: basejump-llama-index-embeddings-openai
Version: 0.3.1.post1
Summary: llama-index embeddings openai integration
Author-email: Your Name <you@example.com>
License-Expression: MIT
License-File: LICENSE
Requires-Python: <4.0,>=3.9
Requires-Dist: basejump-llama-index-core<0.13,>=0.12.0
Requires-Dist: openai>=1.1.0
